{
  "id": "9643db7df0",
  "filename": "collaboration/team/9643db7df0.gif",
  "source": "giphy",
  "source_id": "gGxQTk9koQnRHmYHHF",
  "source_url": "https://giphy.com/gifs/Pac12Network-gGxQTk9koQnRHmYHHF",
  "category": "collaboration",
  "subcategory": "team",
  "tags": [
    "huddle",
    "get-hyped",
    "soccer",
    "team",
    "pep-talk"
  ],
  "tone": [
    "energetic",
    "professional"
  ],
  "primary_emotion": "excitement",
  "recommended_use": "team moments",
  "avoid_if": null,
  "content_rating": "g",
  "duration_seconds": null,
  "dimensions": {
    "width": 480.0,
    "height": 270.0
  },
  "weight_kb": 4542.4,
  "brand_compatible": [
    "Library"
  ],
  "license_note": "Sourced via GIPHY API. Review GIPHY API & Terms of Use (developers.giphy.com/docs/api) before external/client use. Attribution and caching terms may differ for external distribution.",
  "date_added": "2026-07-17T20:13:53.934714+00:00",
  "added_by": "automatic-script",
  "review_pending": false
}
